formulatex/__init__.py
formulatex/math2latex.py
formulatex/statics/__init__.py
formulatex/templates/__init__.py
formulatex-1.1.0.data/data/formulatex_src/statics/Calculation-64.ico
formulatex-1.1.0.data/data/formulatex_src/templates/base.html
formulatex-1.1.0.data/data/formulatex_src/templates/hand_input.html
formulatex-1.1.0.data/data/formulatex_src/templates/history.html
formulatex-1.1.0.data/data/formulatex_src/templates/paste.html
formulatex-1.1.0.dist-info/METADATA
formulatex-1.1.0.dist-info/WHEEL
formulatex-1.1.0.dist-info/top_level.txt
formulatex-1.1.0.dist-info/RECORD
