Metadata-Version: 2.1
Name: formulatex
Version: 1.1.0
Summary: A web app to translate formulas into latex
Home-page: https://github.com/ThomasAtlantis/mathpix-formulatex
Author: Shangyu Liu
Author-email: liushangyu@sjtu.edu.cn
License: MIT
Keywords: latex mathpix formula
Platform: UNKNOWN
Classifier: Intended Audience :: Developers
Classifier: License :: OSI Approved :: MIT License
Classifier: Operating System :: OS Independent
Classifier: Programming Language :: Python :: 3
Requires-Dist: flask
Requires-Dist: pyperclip
Requires-Dist: gevent
